alphaiq_sdk/__init__.py
alphaiq_sdk/client.py
alphaiq_sdk/generative.py
alphaiq_sdk/mapping.py
alphaiq_sdk/models.py
alphaiq_sdk/signals.py
alphaiq_sdk-0.2.9.dist-info/METADATA
alphaiq_sdk-0.2.9.dist-info/WHEEL
alphaiq_sdk-0.2.9.dist-info/top_level.txt
alphaiq_sdk-0.2.9.dist-info/RECORD
