Metadata-Version: 2.1
Name: alphaiq-sdk
Version: 0.2.9
Summary: Access AlphaIQ's generative insights, explainable investment signals, and the Corporate Transparency Score model
Author-email: AlphaIQ <contact@alphaiq.ai>
Project-URL: GitHub, https://github.com/alphaiq-ai/python-sdk
Keywords: risk,AI,fintech,investing,NLP,GenAI
Classifier: Programming Language :: Python
Requires-Python: >=3.9
Requires-Dist: certifi >=14.05.14
Requires-Dist: six >=1.10
Requires-Dist: python-dateutil >=2.5.3
Requires-Dist: setuptools >=21.0.0
Requires-Dist: urllib3 >=1.15.1
